wecopttool/__init__.py
wecopttool/controllers.py
wecopttool/core.py
wecopttool/geom.py
wecopttool/pto.py
wecopttool/utilities.py
wecopttool/waves.py
wecopttool-3.2.0.dist-info/licenses/LICENSE
wecopttool-3.2.0.dist-info/licenses/NOTICE
wecopttool-3.2.0.dist-info/METADATA
wecopttool-3.2.0.dist-info/WHEEL
wecopttool-3.2.0.dist-info/top_level.txt
wecopttool-3.2.0.dist-info/RECORD
