Metadata-Version: 2.4
Name: wecopttool
Version: 3.2.0
Summary: WEC Design Optimization Toolbox
Author: Sandia National Laboratories
License: GNU General Public License v3 (GPLv3)
Project-URL: Documentation, https://sandialabs.github.io/WecOptTool/
Classifier: Programming Language :: Python :: 3
Classifier: License :: OSI Approved :: GNU General Public License v3 (GPLv3)
Classifier: Operating System :: OS Independent
Requires-Python: >=3.8
License-File: LICENSE
License-File: NOTICE
Requires-Dist: numpy<2.0,>=1.20
Requires-Dist: scipy
Requires-Dist: xarray
Requires-Dist: jax
Requires-Dist: capytaine
Requires-Dist: joblib
Requires-Dist: wavespectra>=4.0
Requires-Dist: netcdf4
Provides-Extra: dev
Requires-Dist: pytest; extra == "dev"
Requires-Dist: sphinx; extra == "dev"
Requires-Dist: sphinxcontrib-bibtex; extra == "dev"
Requires-Dist: sphinx_rtd_theme; extra == "dev"
Requires-Dist: jupyter; extra == "dev"
Requires-Dist: nbsphinx; extra == "dev"
Requires-Dist: pandoc; extra == "dev"
Requires-Dist: imageio; extra == "dev"
Requires-Dist: pygifsicle; extra == "dev"
Requires-Dist: jinja2; extra == "dev"
Requires-Dist: nbconvert; extra == "dev"
Provides-Extra: geometry
Requires-Dist: matplotlib; extra == "geometry"
Requires-Dist: meshio; extra == "geometry"
Requires-Dist: gmsh; extra == "geometry"
Requires-Dist: pygmsh; extra == "geometry"
Dynamic: license-file
